indasuite_api_client/__init__.py
indasuite_api_client/api/__init__.py
indasuite_api_client/api/access_zones/__init__.py
indasuite_api_client/api/access_zones/delete_v_1_access_zones_access_zone_id.py
indasuite_api_client/api/access_zones/delete_v_1_access_zones_groups_group_id.py
indasuite_api_client/api/access_zones/get_v1_access_zones.py
indasuite_api_client/api/access_zones/get_v1_access_zones_me.py
indasuite_api_client/api/access_zones/get_v_1_access_zones_access_zone_id.py
indasuite_api_client/api/access_zones/head_v_1_access_zones_access_zone_id_users.py
indasuite_api_client/api/access_zones/patch_v_1_access_zones_access_zone_id_groups.py
indasuite_api_client/api/access_zones/post_v1_access_zones.py
indasuite_api_client/api/access_zones/put_v_1_access_zones_access_zone_id.py
indasuite_api_client/api/annotations/__init__.py
indasuite_api_client/api/annotations/delete_v1_databases_datasource_annotations_id.py
indasuite_api_client/api/annotations/post_v1_databases_datasource_annotations.py
indasuite_api_client/api/annotations/put_v1_databases_datasource_annotations_id.py
indasuite_api_client/api/metrics/__init__.py
indasuite_api_client/api/metrics/delete_v_1_metrics_metric_id.py
indasuite_api_client/api/metrics/get_v1_metrics.py
indasuite_api_client/api/metrics/get_v1_metrics_export_datasource.py
indasuite_api_client/api/metrics/get_v_1_metrics_metric_id.py
indasuite_api_client/api/metrics/patch_v_1_metrics_metric_id.py
indasuite_api_client/api/metrics/post_v1_metrics.py
indasuite_api_client/api/metrics/post_v1_metrics_import_datasource.py
indasuite_api_client/api/metrics/put_v_1_metrics_metric_id.py
indasuite_api_client/api/metrics/put_v_1_metrics_metric_id_rename.py
indasuite_api_client/api/query/__init__.py
indasuite_api_client/api/query/get_v1_databases.py
indasuite_api_client/api/query/post_v1_databases_datasource_query_instant.py
indasuite_api_client/api/query/post_v1_databases_datasource_query_latest.py
indasuite_api_client-1.dist-info/METADATA
indasuite_api_client-1.dist-info/WHEEL
indasuite_api_client-1.dist-info/RECORD
