Metadata-Version: 2.1
Name: indasuite-api-client
Version: 1
Summary: A client library for accessing Indasuite API
Author: Antoine Etchecopar
Author-email: antoine.etchecopar@cva-engineering.com
Requires-Python: >=3.9,<4.0
Classifier: Programming Language :: Python :: 3
Classifier: Programming Language :: Python :: 3.9
Classifier: Programming Language :: Python :: 3.10
Classifier: Programming Language :: Python :: 3.11
Classifier: Programming Language :: Python :: 3.12
Requires-Dist: attrs (>=21.3.0)
Requires-Dist: deprecated (>=1.2.14,<2.0.0)
Requires-Dist: httpx (>=0.20.0,<0.28.0)
Requires-Dist: pandas (>=2.2.2,<3.0.0)
Requires-Dist: python-dateutil (>=2.8.0,<3.0.0)
